bose_soundtouch/__init__.py
bose_soundtouch/client.py
bose_soundtouch/enums.py
bose_soundtouch/exceptions.py
bose_soundtouch/models.py
bose_soundtouch/py.typed
bose_soundtouch/xml_parser.py
bose_soundtouch-0.1.2.dist-info/METADATA
bose_soundtouch-0.1.2.dist-info/WHEEL
bose_soundtouch-0.1.2.dist-info/licenses/LICENSE
bose_soundtouch-0.1.2.dist-info/RECORD
