Metadata-Version: 2.4
Name: bose-soundtouch
Version: 0.1.2
Summary: Python library for controlling Bose SoundTouch speakers via REST API
Author-email: captivus <366332+captivus@users.noreply.github.com>
License-Expression: MIT
License-File: LICENSE
Keywords: audio,bose,home-automation,soundtouch,speaker
Classifier: Development Status :: 3 - Alpha
Classifier: Intended Audience :: Developers
Classifier: License :: OSI Approved :: MIT License
Classifier: Programming Language :: Python :: 3
Classifier: Programming Language :: Python :: 3.12
Classifier: Programming Language :: Python :: 3.13
Classifier: Topic :: Home Automation
Classifier: Typing :: Typed
Requires-Python: >=3.12
Requires-Dist: httpx>=0.28.1
